nvidia_mig_py-0.1.1.dist-info/licenses/LICENSE
pynvmig/__init__.py
pynvmig/cmd_util.py
pynvmig/mig_allocator.py
pynvmig/mig_manager.py
pynvmig/mig_monitor.py
nvidia_mig_py-0.1.1.dist-info/METADATA
nvidia_mig_py-0.1.1.dist-info/WHEEL
nvidia_mig_py-0.1.1.dist-info/top_level.txt
nvidia_mig_py-0.1.1.dist-info/RECORD
