Metadata-Version: 2.4
Name: nvidia-mig-py
Version: 0.1.1
Summary: Python bindings for Nvidia MIG
Author-email: Zhiwei Chu <chi32@purdue.edu>
Classifier: Development Status :: 1 - Planning
Classifier: Intended Audience :: Developers
Classifier: Intended Audience :: System Administrators
Classifier: Environment :: GPU :: NVIDIA CUDA :: 12 :: 12.3
Classifier: Operating System :: POSIX :: Linux
Classifier: Programming Language :: Python
Classifier: Topic :: Software Development :: Libraries :: Python Modules
Classifier: Topic :: System :: Hardware
Classifier: Topic :: System :: Systems Administration
License-File: LICENSE
Requires-Dist: nvidia-ml-py>=12.560.30
Dynamic: license-file
